ebm4subjects/__init__.py
ebm4subjects/analyzer.py
ebm4subjects/chunker.py
ebm4subjects/duckdb_client.py
ebm4subjects/ebm_logging.py
ebm4subjects/ebm_model.py
ebm4subjects/embedding_generator.py
ebm4subjects/prepare_data.py
ebm4subjects-0.5.5.dist-info/METADATA
ebm4subjects-0.5.5.dist-info/WHEEL
ebm4subjects-0.5.5.dist-info/licenses/LICENSE
ebm4subjects-0.5.5.dist-info/RECORD
