Metadata-Version: 2.4
Name: ebm4subjects
Version: 0.5.5
Summary: Embedding Based Matching for Automated Subject Indexing
Author: Deutsche Nationalbibliothek
Maintainer-email: Clemens Rietdorf <c.rietdorf@dnb.de>, Maximilian Kähler <m.kaehler@dnb.de>
License-Expression: EUPL-1.2
License-File: LICENSE
Keywords: code4lib,machine-learning,multilabel-classification,subject-indexing,text-classification
Classifier: Development Status :: 3 - Alpha
Classifier: License :: OSI Approved :: European Union Public Licence 1.2 (EUPL 1.2)
Classifier: Operating System :: OS Independent
Classifier: Programming Language :: Python :: 3
Requires-Python: >=3.10
Requires-Dist: duckdb>=1.3.0
Requires-Dist: nltk~=3.9.1
Requires-Dist: openai>=2.15.0
Requires-Dist: polars>=1.30.0
Requires-Dist: pyarrow>=21.0.0
Requires-Dist: pyoxigraph>=0.4.11
Requires-Dist: rdflib~=7.1.3
Requires-Dist: xgboost>=3.0.2
Provides-Extra: in-process
Requires-Dist: sentence-transformers>=5.0.0; extra == 'in-process'
